pytest_anki/__init__.py
pytest_anki/_addons.py
pytest_anki/_anki.py
pytest_anki/_config.py
pytest_anki/_errors.py
pytest_anki/_launch.py
pytest_anki/_patch.py
pytest_anki/_qt.py
pytest_anki/_session.py
pytest_anki/_types.py
pytest_anki/_util.py
pytest_anki/anki-current.json
pytest_anki/plugin.py
pytest_anki/py.typed
pytest_anki-1.0.0b7.dist-info/entry_points.txt
pytest_anki-1.0.0b7.dist-info/LICENSE
pytest_anki-1.0.0b7.dist-info/WHEEL
pytest_anki-1.0.0b7.dist-info/METADATA
pytest_anki-1.0.0b7.dist-info/RECORD
