Metadata-Version: 2.1
Name: pytest-anki
Version: 1.0.0b7
Summary: A pytest plugin for testing Anki add-ons
Home-page: https://github.com/glutanimate/pytest-anki
License: AGPL-3.0-or-later
Keywords: anki,development,testing,test,pytest
Author: Aristotelis P. (Glutanimate)
Requires-Python: >=3.8,<4.0
Classifier: Development Status :: 4 - Beta
Classifier: Framework :: Pytest
Classifier: Intended Audience :: Developers
Classifier: License :: OSI Approved :: GNU Affero General Public License v3 or later (AGPLv3+)
Classifier: Programming Language :: Python :: 3
Classifier: Programming Language :: Python :: 3.10
Classifier: Programming Language :: Python :: 3.8
Classifier: Programming Language :: Python :: 3.9
Classifier: Topic :: Software Development :: Quality Assurance
Classifier: Topic :: Software Development :: Testing
Classifier: Topic :: Software Development :: User Interfaces
Requires-Dist: anki (>=2.1.28)
Requires-Dist: aqt (>=2.1.28)
Requires-Dist: packaging (>=21.3,<22.0)
Requires-Dist: pytest (>=3.5.0)
Requires-Dist: pytest-forked (>=1.3.0,<2.0.0)
Requires-Dist: pytest-qt (>=4.0.2,<5.0.0)
Requires-Dist: pytest-xdist (>=2.3.0,<3.0.0)
Requires-Dist: pytest-xvfb (>=2.0.0,<3.0.0)
Requires-Dist: selenium (>=3.141.0,<4.0.0)
Project-URL: Repository, https://github.com/glutanimate/pytest-anki
